Metadata-Version: 2.4
Name: package_string_aziz_dhif
Version: 0.1.0
Summary: 
Author: AzizDHIF
Author-email: azizdhif686@gmail.com
Requires-Python: >=3.11
Classifier: Programming Language :: Python :: 3
Classifier: Programming Language :: Python :: 3.11
Classifier: Programming Language :: Python :: 3.12
Classifier: Programming Language :: Python :: 3.13
Classifier: Programming Language :: Python :: 3.14
Requires-Dist: pytest (>=9.0.2,<10.0.0)
Requires-Dist: pytest-cov (>=7.0.0,<8.0.0)
